mridata/__init__.py
mridata/account.py
mridata/download.py
mridata/upload.py
mridata-0.2.2.data/scripts/mridata
mridata-0.2.2.dist-info/METADATA
mridata-0.2.2.dist-info/RECORD
mridata-0.2.2.dist-info/WHEEL
mridata-0.2.2.dist-info/top_level.txt
