Metadata-Version: 2.1
Name: mridata
Version: 0.2.2
Summary: Python command line interface for downloading and uploading to mridata.org.
Home-page: http://github.com/mikgroup/mridata-python
Author: Frank Ong
Author-email: frankong@berkeley.edu
License: BSD
Platform: UNKNOWN
Classifier: Programming Language :: Python :: 3
Classifier: License :: OSI Approved :: BSD License
Classifier: Operating System :: OS Independent
Requires-Dist: requests
Requires-Dist: boto3
Requires-Dist: tqdm
